{
    "annotations": {
      "list": [
        {
          "builtIn": 1,
          "datasource": {
            "type": "grafana",
            "uid": "-- Grafana --"
          },
          "enable": true,
          "hide": true,
          "iconColor": "rgba(0, 211, 255, 1)",
          "name": "Annotations & Alerts",
          "target": {
            "limit": 100,
            "matchAny": false,
            "tags": [],
            "type": "dashboard"
          },
          "type": "dashboard"
        }
      ]
    },
    "editable": true,
    "fiscalYearStartMonth": 0,
    "graphTooltip": 0,
    "id": 9,
    "links": [],
    "liveNow": false,
    "panels": [
      {
        "datasource": {
          "type": "prometheus",
          "uid": "000000001"
        },
        "description": "",
        "fieldConfig": {
          "defaults": {
            "color": {
              "mode": "thresholds"
            },
            "mappings": [],
            "thresholds": {
              "mode": "absolute",
              "steps": [
                {
                  "color": "green",
                  "value": null
                },
                {
                  "color": "yellow",
                  "value": 500
                },
                {
                  "color": "orange",
                  "value": 1000
                },
                {
                  "color": "red",
                  "value": 2000
                }
              ]
            },
            "unit": "watt"
          },
          "overrides": []
        },
        "gridPos": {
          "h": 7,
          "w": 5,
          "x": 0,
          "y": 0
        },
        "id": 12,
        "options": {
          "orientation": "auto",
          "reduceOptions": {
            "calcs": [
              "lastNotNull"
            ],
            "fields": "",
            "values": false
          },
          "showThresholdLabels": false,
          "showThresholdMarkers": true
        },
        "pluginVersion": "9.1.0",
        "targets": [
          {
            "datasource": {
              "type": "prometheus",
              "uid": "000000001"
            },
            "editorMode": "code",
            "expr": "electric_meter_current{meter!=\"0\"} * electric_meter_voltage{meter!=\"0\"}",
            "legendFormat": "__auto",
            "range": true,
            "refId": "A"
          }
        ],
        "title": "Aktuelle Leistung",
        "type": "gauge"
      },
      {
        "datasource": {
          "type": "prometheus",
          "uid": "000000001"
        },
        "fieldConfig": {
          "defaults": {
            "color": {
              "mode": "palette-classic"
            },
            "custom": {
              "axisCenteredZero": false,
              "axisColorMode": "text",
              "axisLabel": "",
              "axisPlacement": "auto",
              "barAlignment": 0,
              "drawStyle": "line",
              "fillOpacity": 10,
              "gradientMode": "opacity",
              "hideFrom": {
                "legend": false,
                "tooltip": false,
                "viz": false
              },
              "lineInterpolation": "linear",
              "lineWidth": 1,
              "pointSize": 5,
              "scaleDistribution": {
                "type": "linear"
              },
              "showPoints": "never",
              "spanNulls": false,
              "stacking": {
                "group": "A",
                "mode": "none"
              },
              "thresholdsStyle": {
                "mode": "off"
              }
            },
            "links": [],
            "mappings": [],
            "thresholds": {
              "mode": "absolute",
              "steps": [
                {
                  "color": "green",
                  "value": null
                },
                {
                  "color": "red",
                  "value": 80
                }
              ]
            },
            "unit": "watt"
          },
          "overrides": []
        },
        "gridPos": {
          "h": 7,
          "w": 15,
          "x": 5,
          "y": 0
        },
        "id": 2,
        "options": {
          "legend": {
            "calcs": [
              "mean",
              "lastNotNull",
              "max"
            ],
            "displayMode": "table",
            "placement": "bottom",
            "showLegend": true
          },
          "tooltip": {
            "mode": "multi",
            "sort": "desc"
          }
        },
        "pluginVersion": "9.0.4",
        "targets": [
          {
            "datasource": {
              "type": "prometheus",
              "uid": "000000001"
            },
            "editorMode": "code",
            "expr": "sum by (label) (avg_over_time(electric_meter_current{meter!=\"0\"}[1m])*230)",
            "interval": "",
            "legendFormat": "Aktuell",
            "range": true,
            "refId": "A"
          },
          {
            "datasource": {
              "type": "prometheus",
              "uid": "000000001"
            },
            "editorMode": "code",
            "expr": "avg_over_time((electric_meter_voltage{meter!=\"0\"} * electric_meter_current{meter!=\"0\"})[1h:1m])",
            "hide": false,
            "legendFormat": "Durchschnittlich",
            "range": true,
            "refId": "B"
          }
        ],
        "title": "Verbauch",
        "type": "timeseries"
      },
      {
        "datasource": {
          "type": "prometheus",
          "uid": "000000001"
        },
        "description": "",
        "fieldConfig": {
          "defaults": {
            "color": {
              "mode": "thresholds"
            },
            "decimals": 3,
            "mappings": [],
            "thresholds": {
              "mode": "absolute",
              "steps": [
                {
                  "color": "green",
                  "value": null
                }
              ]
            },
            "unit": "kwatth"
          },
          "overrides": []
        },
        "gridPos": {
          "h": 7,
          "w": 5,
          "x": 0,
          "y": 7
        },
        "id": 14,
        "options": {
          "colorMode": "value",
          "graphMode": "area",
          "justifyMode": "auto",
          "orientation": "auto",
          "reduceOptions": {
            "calcs": [
              "lastNotNull"
            ],
            "fields": "",
            "values": false
          },
          "textMode": "auto"
        },
        "pluginVersion": "9.1.0",
        "targets": [
          {
            "datasource": {
              "type": "prometheus",
              "uid": "000000001"
            },
            "editorMode": "code",
            "expr": "electric_meter_total{meter!=\"0\"}",
            "legendFormat": "__auto",
            "range": true,
            "refId": "A"
          }
        ],
        "title": "Z채hlerstand",
        "type": "stat"
      },
      {
        "datasource": {
          "type": "prometheus",
          "uid": "000000001"
        },
        "fieldConfig": {
          "defaults": {
            "color": {
              "mode": "palette-classic"
            },
            "custom": {
              "axisCenteredZero": false,
              "axisColorMode": "series",
              "axisLabel": "Kosten",
              "axisPlacement": "auto",
              "barAlignment": -1,
              "drawStyle": "line",
              "fillOpacity": 20,
              "gradientMode": "none",
              "hideFrom": {
                "legend": false,
                "tooltip": false,
                "viz": false
              },
              "lineInterpolation": "linear",
              "lineStyle": {
                "fill": "solid"
              },
              "lineWidth": 1,
              "pointSize": 5,
              "scaleDistribution": {
                "type": "linear"
              },
              "showPoints": "always",
              "spanNulls": false,
              "stacking": {
                "group": "A",
                "mode": "none"
              },
              "thresholdsStyle": {
                "mode": "off"
              }
            },
            "decimals": 2,
            "mappings": [],
            "min": 0,
            "thresholds": {
              "mode": "absolute",
              "steps": [
                {
                  "color": "green",
                  "value": null
                },
                {
                  "color": "red",
                  "value": 80
                }
              ]
            },
            "unit": "currencyEUR"
          },
          "overrides": []
        },
        "gridPos": {
          "h": 7,
          "w": 15,
          "x": 5,
          "y": 7
        },
        "id": 18,
        "options": {
          "legend": {
            "calcs": [],
            "displayMode": "list",
            "placement": "bottom",
            "showLegend": false
          },
          "tooltip": {
            "mode": "single",
            "sort": "none"
          }
        },
        "targets": [
          {
            "datasource": {
              "type": "prometheus",
              "uid": "000000001"
            },
            "editorMode": "code",
            "exemplar": false,
            "expr": "delta(electric_meter_total{meter!=\"0\"}[$__interval]) * 0.3",
            "format": "table",
            "hide": false,
            "instant": false,
            "interval": "1d",
            "legendFormat": "{{label_name}}",
            "range": true,
            "refId": "A"
          }
        ],
        "title": "Kosten pro Tag",
        "type": "timeseries"
      },
      {
        "datasource": {
          "type": "prometheus",
          "uid": "000000001"
        },
        "fieldConfig": {
          "defaults": {
            "color": {
              "mode": "thresholds"
            },
            "mappings": [],
            "thresholds": {
              "mode": "absolute",
              "steps": [
                {
                  "color": "green",
                  "value": null
                },
                {
                  "color": "red",
                  "value": 80
                }
              ]
            },
            "unit": "amp"
          },
          "overrides": []
        },
        "gridPos": {
          "h": 6,
          "w": 5,
          "x": 0,
          "y": 14
        },
        "id": 16,
        "options": {
          "orientation": "auto",
          "reduceOptions": {
            "calcs": [
              "lastNotNull"
            ],
            "fields": "",
            "values": false
          },
          "showThresholdLabels": false,
          "showThresholdMarkers": false
        },
        "pluginVersion": "9.1.0",
        "targets": [
          {
            "datasource": {
              "type": "prometheus",
              "uid": "000000001"
            },
            "editorMode": "code",
            "expr": "electric_meter_current{meter!=\"0\"}",
            "legendFormat": "__auto",
            "range": true,
            "refId": "A"
          }
        ],
        "title": "Stromst채rke",
        "type": "gauge"
      },
      {
        "datasource": {
          "type": "prometheus",
          "uid": "000000001"
        },
        "fieldConfig": {
          "defaults": {
            "color": {
              "mode": "palette-classic"
            },
            "custom": {
              "axisCenteredZero": false,
              "axisColorMode": "text",
              "axisLabel": "",
              "axisPlacement": "auto",
              "barAlignment": 0,
              "drawStyle": "line",
              "fillOpacity": 0,
              "gradientMode": "none",
              "hideFrom": {
                "legend": false,
                "tooltip": false,
                "viz": false
              },
              "lineInterpolation": "linear",
              "lineWidth": 1,
              "pointSize": 5,
              "scaleDistribution": {
                "type": "linear"
              },
              "showPoints": "auto",
              "spanNulls": false,
              "stacking": {
                "group": "A",
                "mode": "none"
              },
              "thresholdsStyle": {
                "mode": "off"
              }
            },
            "mappings": [],
            "thresholds": {
              "mode": "absolute",
              "steps": [
                {
                  "color": "green",
                  "value": null
                },
                {
                  "color": "red",
                  "value": 80
                }
              ]
            }
          },
          "overrides": []
        },
        "gridPos": {
          "h": 6,
          "w": 15,
          "x": 5,
          "y": 14
        },
        "id": 2,
        "options": {
          "legend": {
            "calcs": [],
            "displayMode": "list",
            "placement": "bottom",
            "showLegend": true
          },
          "tooltip": {
            "mode": "single",
            "sort": "none"
          }
        },
        "targets": [
          {
            "datasource": {
              "type": "prometheus",
              "uid": "000000001"
            },
            "editorMode": "builder",
            "exemplar": false,
            "expr": "electric_meter_current{meter=\"70035089\"}",
            "legendFormat": "Stromst채rke [A]",
            "range": true,
            "refId": "A"
          }
        ],
        "title": "Stromst채rke",
        "type": "timeseries"
      },
      {
        "datasource": {
          "type": "prometheus",
          "uid": "000000001"
        },
        "fieldConfig": {
          "defaults": {
            "color": {
              "mode": "thresholds"
            },
            "mappings": [],
            "max": 245,
            "min": 215,
            "thresholds": {
              "mode": "absolute",
              "steps": [
                {
                  "color": "red"
                },
                {
                  "color": "yellow",
                  "value": 220
                },
                {
                  "color": "green",
                  "value": 225
                },
                {
                  "color": "#EAB839",
                  "value": 235
                },
                {
                  "color": "red",
                  "value": 240
                }
              ]
            },
            "unit": "volt"
          },
          "overrides": []
        },
        "gridPos": {
          "h": 6,
          "w": 5,
          "x": 0,
          "y": 20
        },
        "id": 10,
        "options": {
          "orientation": "horizontal",
          "reduceOptions": {
            "calcs": [
              "lastNotNull"
            ],
            "fields": "",
            "values": false
          },
          "showThresholdLabels": false,
          "showThresholdMarkers": true
        },
        "pluginVersion": "9.1.0",
        "targets": [
          {
            "datasource": {
              "type": "prometheus",
              "uid": "000000001"
            },
            "editorMode": "code",
            "expr": "electric_meter_voltage{meter!=\"0\"}",
            "range": true,
            "refId": "A"
          }
        ],
        "title": "Spannung",
        "type": "gauge"
      },
      {
        "datasource": {
          "type": "prometheus",
          "uid": "000000001"
        },
        "fieldConfig": {
          "defaults": {
            "color": {
              "mode": "palette-classic"
            },
            "custom": {
              "axisCenteredZero": false,
              "axisColorMode": "text",
              "axisLabel": "",
              "axisPlacement": "auto",
              "barAlignment": 0,
              "drawStyle": "line",
              "fillOpacity": 0,
              "gradientMode": "none",
              "hideFrom": {
                "legend": false,
                "tooltip": false,
                "viz": false
              },
              "lineInterpolation": "linear",
              "lineWidth": 1,
              "pointSize": 5,
              "scaleDistribution": {
                "type": "linear"
              },
              "showPoints": "auto",
              "spanNulls": false,
              "stacking": {
                "group": "A",
                "mode": "none"
              },
              "thresholdsStyle": {
                "mode": "off"
              }
            },
            "mappings": [],
            "thresholds": {
              "mode": "absolute",
              "steps": [
                {
                  "color": "green"
                },
                {
                  "color": "red",
                  "value": 80
                }
              ]
            }
          },
          "overrides": []
        },
        "gridPos": {
          "h": 6,
          "w": 15,
          "x": 5,
          "y": 20
        },
        "id": 8,
        "options": {
          "legend": {
            "calcs": [],
            "displayMode": "list",
            "placement": "bottom",
            "showLegend": true
          },
          "tooltip": {
            "mode": "single",
            "sort": "none"
          }
        },
        "targets": [
          {
            "datasource": {
              "type": "prometheus",
              "uid": "000000001"
            },
            "editorMode": "code",
            "expr": "electric_meter_voltage{meter!=\"0\"}",
            "legendFormat": "Spannung [V]",
            "range": true,
            "refId": "A"
          }
        ],
        "title": "Spannung",
        "type": "timeseries"
      }
    ],
    "refresh": "10s",
    "schemaVersion": 37,
    "style": "dark",
    "tags": [],
    "templating": {
      "list": []
    },
    "time": {
      "from": "now-3h",
      "to": "now"
    },
    "timepicker": {},
    "timezone": "",
    "title": "Stromverbrauch",
    "uid": "gZuxCCR4k",
    "version": 10,
    "weekStart": ""
  }